banddownfolder/__init__.py
banddownfolder/gen_atoms.py
banddownfolder/structurebuilder.py
banddownfolder/math/__init__.py
banddownfolder/math/geometry.py
banddownfolder/math/linalg.py
banddownfolder/math/pert.py
banddownfolder/plot/__init__.py
banddownfolder/plot/plot.py
banddownfolder/plot/testpath.py
banddownfolder/scdm/__init__.py
banddownfolder/scdm/density_scdmk.py
banddownfolder/scdm/downfolder.py
banddownfolder/scdm/eigen_modifer.py
banddownfolder/scdm/ijR_potential.py
banddownfolder/scdm/lwf.py
banddownfolder/scdm/myTB.py
banddownfolder/scdm/mytb.py
banddownfolder/scdm/normalize.py
banddownfolder/scdm/scdmk.py
banddownfolder/scdm/w90_parser.py
banddownfolder/utils/__init__.py
banddownfolder/utils/kpoints.py
banddownfolder/utils/nckit.py
banddownfolder/utils/supercell.py
banddownfolder/utils/symbol.py
banddownfolder/wrapper/__init__.py
banddownfolder/wrapper/gpawwrapper.py
banddownfolder/wrapper/ifcwrapper.py
banddownfolder/wrapper/ijR.py
banddownfolder/wrapper/myTB.py
banddownfolder/wrapper/phonopywrapper.py
banddownfolder/wrapper/pythtb.py
banddownfolder/wrapper/sislwrapper.py
banddownfolder/wrapper/utils.py
banddownfolder/wrapper/w90_parser.py
banddownfolder/wrapper/wannier90.py
banddownfolder-0.1.4.data/scripts/phonopy_to_netcdf.py
banddownfolder-0.1.4.dist-info/LICENSE
banddownfolder-0.1.4.dist-info/METADATA
banddownfolder-0.1.4.dist-info/WHEEL
banddownfolder-0.1.4.dist-info/top_level.txt
banddownfolder-0.1.4.dist-info/RECORD
